mim_nlp/__init__.py
mim_nlp/classifier/nn/__init__.py
mim_nlp/classifier/nn/nn_classifier.py
mim_nlp/classifier/svm/__init__.py
mim_nlp/classifier/svm/svm.py
mim_nlp/classifier/svm/svm_explainer.py
mim_nlp/classifier/svm/svm_reduction.py
mim_nlp/general_utils.py
mim_nlp/models/__init__.py
mim_nlp/models/classifier.py
mim_nlp/models/model.py
mim_nlp/models/regressor.py
mim_nlp/models/seq2seq.py
mim_nlp/models/summarizer.py
mim_nlp/neural_network/__init__.py
mim_nlp/neural_network/nn_model.py
mim_nlp/neural_network/nn_module.py
mim_nlp/preprocessing/__init__.py
mim_nlp/preprocessing/cleaning_functions.py
mim_nlp/preprocessing/duplicates.py
mim_nlp/preprocessing/exceptions.py
mim_nlp/preprocessing/lemmatize.py
mim_nlp/preprocessing/text_cleaner.py
mim_nlp/preprocessing/utils.py
mim_nlp/regressor/__init__.py
mim_nlp/regressor/auto_regressor.py
mim_nlp/regressor/nn_regressor.py
mim_nlp/seq2seq/__init__.py
mim_nlp/seq2seq/auto_summarizer.py
mim_nlp/seq2seq/data.py
mim_nlp-0.2.1.dist-info/LICENSE
mim_nlp-0.2.1.dist-info/METADATA
mim_nlp-0.2.1.dist-info/WHEEL
mim_nlp-0.2.1.dist-info/RECORD
