Metadata-Version: 2.1
Name: mim-nlp
Version: 0.2.1
Summary: A Python package with ready-to-use models for various NLP tasks and text preprocessing utilities. The implementation allows fine-tuning.
Home-page: https://github.com/mim-solutions/mim_nlp
License: MIT
Keywords: nlp,natural-language-processing,machine-learning,deep-learning,neural-network,transfer-learning,text-classification,text-regression,seq2seq,summarization,text,text-preprocessing,text-cleaning,lemmatization,deduplication,transformers,pytorch
Author: Michał Brzozowski
Requires-Python: >=3.9,<4.0
Classifier: License :: OSI Approved :: MIT License
Classifier: Operating System :: OS Independent
Classifier: Programming Language :: Python :: 3
Classifier: Programming Language :: Python :: 3.9
Classifier: Programming Language :: Python :: 3.10
Classifier: Programming Language :: Python :: 3.11
Provides-Extra: classifier
Provides-Extra: preprocessing
Provides-Extra: regressor
Provides-Extra: seq2seq
Provides-Extra: svm
Requires-Dist: accelerate (>=0.20.1,<0.21.0) ; extra == "regressor" or extra == "seq2seq"
Requires-Dist: advertools (>=0.13.2,<0.14.0) ; extra == "preprocessing"
Requires-Dist: gensim (>=4.3.1,<5.0.0) ; extra == "preprocessing"
Requires-Dist: loguru (>=0.7.0,<0.8.0) ; extra == "seq2seq"
Requires-Dist: matplotlib (>=3.7.1,<4.0.0) ; extra == "svm" or extra == "classifier"
Requires-Dist: more-itertools (>=9.1.0,<10.0.0) ; extra == "seq2seq"
Requires-Dist: morfeusz2 (>=1.99.7,<2.0.0) ; extra == "preprocessing"
Requires-Dist: numpy (>=1.24.1,<2.0.0)
Requires-Dist: pytorch-lightning (>=1.5) ; extra == "classifier" or extra == "regressor"
Requires-Dist: scikit-learn (>=1.2.2,<2.0.0) ; extra == "svm" or extra == "classifier" or extra == "regressor" or extra == "seq2seq"
Requires-Dist: scipy (>=1.10.1,<2.0.0) ; extra == "preprocessing"
Requires-Dist: torch (>=1.7.1) ; extra == "classifier" or extra == "regressor" or extra == "seq2seq"
Requires-Dist: torchmetrics (>=1.0.0,<2.0.0) ; extra == "classifier" or extra == "regressor"
Requires-Dist: tqdm (>=4.65.0,<5.0.0) ; extra == "seq2seq"
Requires-Dist: transformers (>=4.29.2,<5.0.0) ; extra == "classifier" or extra == "regressor" or extra == "seq2seq"
Project-URL: Bug Tracker, https://github.com/mim-solutions/mim_nlp/issues
Project-URL: Repository, https://github.com/mim-solutions/mim_nlp
